langchainplus_sdk/__init__.py
langchainplus_sdk/cli/__init__.py
langchainplus_sdk/cli/docker-compose.dev.yaml
langchainplus_sdk/cli/docker-compose.ngrok.yaml
langchainplus_sdk/cli/docker-compose.yaml
langchainplus_sdk/cli/main.py
langchainplus_sdk/client.py
langchainplus_sdk/evaluation/__init__.py
langchainplus_sdk/evaluation/evaluator.py
langchainplus_sdk/evaluation/string_evaluator.py
langchainplus_sdk/openai.py
langchainplus_sdk/run_helpers.py
langchainplus_sdk/run_trees.py
langchainplus_sdk/schemas.py
langchainplus_sdk/utils.py
langchainplus_sdk-0.0.21.dist-info/METADATA
langchainplus_sdk-0.0.21.dist-info/WHEEL
langchainplus_sdk-0.0.21.dist-info/entry_points.txt
langchainplus_sdk-0.0.21.dist-info/RECORD
